Regularization_Methods_for_HVIs/Algorithm.py
Regularization_Methods_for_HVIs/AuxProblemSolver.py
Regularization_Methods_for_HVIs/Operators.py
Regularization_Methods_for_HVIs/Problem.py
Regularization_Methods_for_HVIs/Scheduler.py
Regularization_Methods_for_HVIs/SplittingSchemes.py
Regularization_Methods_for_HVIs/__init__.py
regularization_methods_for_hvis-1.2.dist-info/licenses/LICENSE
regularization_methods_for_hvis-1.2.dist-info/METADATA
regularization_methods_for_hvis-1.2.dist-info/WHEEL
regularization_methods_for_hvis-1.2.dist-info/top_level.txt
regularization_methods_for_hvis-1.2.dist-info/RECORD
