Metadata-Version: 2.4
Name: Regularization_Methods_for_HVIs
Version: 1.2
Summary: Package aimed at solving variational inequalities over the solution set of a monotone inclusion.
Author-email: Daniel Cortild <daniel.cortild@maths.ox.ac.uk>, Meggie Marschner <meggie.marschner@uni-mannheim.de>, Mathias Staudigl <m.staudigl@uni-mannheim.de>
License-Expression: MIT
Project-URL: Homepage, https://github.com/Hierarchical-VIs/Regularization-Methods-for-HVIs
Project-URL: Issues, https://github.com/Hierarchical-VIs/Regularization-Methods-for-HVIs/issues
Classifier: Programming Language :: Python :: 3
Classifier: Operating System :: OS Independent
Requires-Python: >=3.9
License-File: LICENSE
Requires-Dist: numpy
Requires-Dist: scipy
Dynamic: license-file
